misc/PropertyMap.py
misc/__init__.py
misc/positions.py
pycromanager/__init__.py
pycromanager/_version.py
pycromanager/headless.py
pycromanager/mm_java_classes.py
pycromanager/acquisition/RAMStorage_java.py
pycromanager/acquisition/__init__.py
pycromanager/acquisition/acq_constructor.py
pycromanager/acquisition/acq_future.py
pycromanager/acquisition/acquisition_superclass.py
pycromanager/acquisition/java_backend_acquisitions.py
pycromanager/acquisition/napari_util.py
pycromanager/acquisition/python_backend_acquisitions.py
pycromanager/acquisition/acq_eng_py/__init__.py
pycromanager/acquisition/acq_eng_py/internal/__init__.py
pycromanager/acquisition/acq_eng_py/internal/engine.py
pycromanager/acquisition/acq_eng_py/internal/hardware_sequences.py
pycromanager/acquisition/acq_eng_py/internal/notification_handler.py
pycromanager/acquisition/acq_eng_py/main/AcqEngPy_Acquisition.py
pycromanager/acquisition/acq_eng_py/main/__init__.py
pycromanager/acquisition/acq_eng_py/main/acq_eng_metadata.py
pycromanager/acquisition/acq_eng_py/main/acq_notification.py
pycromanager/acquisition/acq_eng_py/main/acquisition_event.py
pycromanager/test/__init__.py
pycromanager/test/conftest.py
pycromanager/test/test_MDA_events.py
pycromanager/test/test_acquisition.py
pycromanager/test/test_callback_functions.py
pycromanager/test/test_notifications_futures.py
pycromanager/test/test_startup.py
pycromanager/test/test_viewer.py
pycromanager-1.0.2.dist-info/LICENSE
pycromanager-1.0.2.dist-info/METADATA
pycromanager-1.0.2.dist-info/WHEEL
pycromanager-1.0.2.dist-info/top_level.txt
pycromanager-1.0.2.dist-info/RECORD
