Metadata-Version: 2.2
Name: pycromanager
Version: 1.0.2
Summary: Open source microscope control using python
Home-page: https://github.com/micro-manager/pycro-manager
Author: Henry Pinkard
Author-email: henry.pinkard@gmail.com
Classifier: Programming Language :: Python :: 3.7
Classifier: Programming Language :: Python :: 3.8
Classifier: Programming Language :: Python :: 3.9
Classifier: Programming Language :: Python :: 3.10
Classifier: Programming Language :: Python :: 3.11
Classifier: Development Status :: 3 - Alpha
Classifier: License :: OSI Approved :: BSD License
Classifier: Operating System :: OS Independent
Requires-Python: >=3.6
License-File: LICENSE
Requires-Dist: numpy
Requires-Dist: dask[array]>=2022.2.0
Requires-Dist: ndstorage>=0.1.6
Requires-Dist: docstring-inheritance
Requires-Dist: mmpycorex
Requires-Dist: sortedcontainers
Provides-Extra: dev
Requires-Dist: pytest; extra == "dev"
Requires-Dist: wget; extra == "dev"
Requires-Dist: requests; extra == "dev"
Requires-Dist: napari; extra == "dev"
Dynamic: author
Dynamic: author-email
Dynamic: classifier
Dynamic: description
Dynamic: description-content-type
Dynamic: home-page
Dynamic: provides-extra
Dynamic: requires-dist
Dynamic: requires-python
Dynamic: summary
